{
  "openapi": "3.0.1",
  "info": {
    "title": "ElectroComApi",
    "version": "1.0"
  },
  "paths": {
    "/api/OrderConfirmation": {
      "post": {
        "tags": [
          "OrderConfirmation"
        ],
        "requestBody": {
          "content": {
            "application/json": {
              "schema": {
                "$ref": "#/components/schemas/QuotationResponseDto"
              }
            },
            "text/json": {
              "schema": {
                "$ref": "#/components/schemas/QuotationResponseDto"
              }
            },
            "application/*+json": {
              "schema": {
                "$ref": "#/components/schemas/QuotationResponseDto"
              }
            }
          }
        },
        "responses": {
          "200": {
            "description": "OK"
          }
        }
      },
      "get": {
        "tags": [
          "OrderConfirmation"
        ],
        "responses": {
          "200": {
            "description": "OK"
          }
        }
      }
    },
    "/api/OrderConfirmation/{orderId}": {
      "get": {
        "tags": [
          "OrderConfirmation"
        ],
        "parameters": [
          {
            "name": "orderId",
            "in": "path",
            "required": true,
            "schema": {
              "type": "integer",
              "format": "int32"
            }
          }
        ],
        "responses": {
          "200": {
            "description": "OK"
          }
        }
      },
      "put": {
        "tags": [
          "OrderConfirmation"
        ],
        "parameters": [
          {
            "name": "orderId",
            "in": "path",
            "required": true,
            "schema": {
              "type": "integer",
              "format": "int32"
            }
          }
        ],
        "requestBody": {
          "content": {
            "application/json": {
              "schema": {
                "$ref": "#/components/schemas/OrderConfirmationDto"
              }
            },
            "text/json": {
              "schema": {
                "$ref": "#/components/schemas/OrderConfirmationDto"
              }
            },
            "application/*+json": {
              "schema": {
                "$ref": "#/components/schemas/OrderConfirmationDto"
              }
            }
          }
        },
        "responses": {
          "200": {
            "description": "OK"
          }
        }
      },
      "delete": {
        "tags": [
          "OrderConfirmation"
        ],
        "parameters": [
          {
            "name": "orderId",
            "in": "path",
            "required": true,
            "schema": {
              "type": "integer",
              "format": "int32"
            }
          }
        ],
        "responses": {
          "200": {
            "description": "OK"
          }
        }
      }
    },
    "/api/QuoRequest": {
      "post": {
        "tags": [
          "QuoRequest"
        ],
        "requestBody": {
          "content": {
            "application/json": {
              "schema": {
                "$ref": "#/components/schemas/QuotationRequestDto"
              }
            },
            "text/json": {
              "schema": {
                "$ref": "#/components/schemas/QuotationRequestDto"
              }
            },
            "application/*+json": {
              "schema": {
                "$ref": "#/components/schemas/QuotationRequestDto"
              }
            }
          }
        },
        "responses": {
          "200": {
            "description": "OK"
          }
        }
      },
      "get": {
        "tags": [
          "QuoRequest"
        ],
        "responses": {
          "200": {
            "description": "OK"
          }
        }
      }
    },
    "/api/QuoRequest/{id}": {
      "get": {
        "tags": [
          "QuoRequest"
        ],
        "parameters": [
          {
            "name": "id",
            "in": "path",
            "required": true,
            "schema": {
              "type": "integer",
              "format": "int32"
            }
          }
        ],
        "responses": {
          "200": {
            "description": "OK"
          }
        }
      },
      "put": {
        "tags": [
          "QuoRequest"
        ],
        "parameters": [
          {
            "name": "id",
            "in": "path",
            "required": true,
            "schema": {
              "type": "integer",
              "format": "int32"
            }
          }
        ],
        "requestBody": {
          "content": {
            "application/json": {
              "schema": {
                "$ref": "#/components/schemas/QuotationRequestDto"
              }
            },
            "text/json": {
              "schema": {
                "$ref": "#/components/schemas/QuotationRequestDto"
              }
            },
            "application/*+json": {
              "schema": {
                "$ref": "#/components/schemas/QuotationRequestDto"
              }
            }
          }
        },
        "responses": {
          "200": {
            "description": "OK"
          }
        }
      },
      "delete": {
        "tags": [
          "QuoRequest"
        ],
        "parameters": [
          {
            "name": "id",
            "in": "path",
            "required": true,
            "schema": {
              "type": "integer",
              "format": "int32"
            }
          }
        ],
        "responses": {
          "200": {
            "description": "OK"
          }
        }
      }
    },
    "/api/QuoResponse": {
      "get": {
        "tags": [
          "QuoResponse"
        ],
        "responses": {
          "200": {
            "description": "OK"
          }
        }
      },
      "post": {
        "tags": [
          "QuoResponse"
        ],
        "requestBody": {
          "content": {
            "application/json": {
              "schema": {
                "$ref": "#/components/schemas/QuotationResponseDto"
              }
            },
            "text/json": {
              "schema": {
                "$ref": "#/components/schemas/QuotationResponseDto"
              }
            },
            "application/*+json": {
              "schema": {
                "$ref": "#/components/schemas/QuotationResponseDto"
              }
            }
          }
        },
        "responses": {
          "200": {
            "description": "OK"
          }
        }
      }
    },
    "/api/QuoResponse/{id}": {
      "get": {
        "tags": [
          "QuoResponse"
        ],
        "parameters": [
          {
            "name": "id",
            "in": "path",
            "required": true,
            "schema": {
              "type": "integer",
              "format": "int32"
            }
          }
        ],
        "responses": {
          "200": {
            "description": "OK"
          }
        }
      },
      "put": {
        "tags": [
          "QuoResponse"
        ],
        "parameters": [
          {
            "name": "id",
            "in": "path",
            "required": true,
            "schema": {
              "type": "integer",
              "format": "int32"
            }
          }
        ],
        "requestBody": {
          "content": {
            "application/json": {
              "schema": {
                "$ref": "#/components/schemas/QuotationResponseDto"
              }
            },
            "text/json": {
              "schema": {
                "$ref": "#/components/schemas/QuotationResponseDto"
              }
            },
            "application/*+json": {
              "schema": {
                "$ref": "#/components/schemas/QuotationResponseDto"
              }
            }
          }
        },
        "responses": {
          "200": {
            "description": "OK"
          }
        }
      },
      "delete": {
        "tags": [
          "QuoResponse"
        ],
        "parameters": [
          {
            "name": "id",
            "in": "path",
            "required": true,
            "schema": {
              "type": "integer",
              "format": "int32"
            }
          }
        ],
        "responses": {
          "200": {
            "description": "OK"
          }
        }
      }
    }
  },
  "components": {
    "schemas": {
      "ConfirmedProductDto": {
        "type": "object",
        "properties": {
          "productId": {
            "type": "string",
            "nullable": true
          },
          "quantityConfirmed": {
            "type": "integer",
            "format": "int32"
          },
          "status": {
            "type": "string",
            "nullable": true
          }
        },
        "additionalProperties": false
      },
      "OrderConfirmationDto": {
        "type": "object",
        "properties": {
          "orderId": {
            "type": "integer",
            "format": "int32"
          },
          "requestId": {
            "type": "string",
            "nullable": true
          },
          "confirmationDate": {
            "type": "string",
            "format": "date-time"
          },
          "status": {
            "type": "string",
            "nullable": true
          },
          "confirmedProducts": {
            "type": "array",
            "items": {
              "$ref": "#/components/schemas/ConfirmedProductDto"
            },
            "nullable": true
          }
        },
        "additionalProperties": false
      },
      "ProductQuoteInfoReadDto": {
        "type": "object",
        "properties": {
          "productId": {
            "type": "string",
            "nullable": true
          },
          "pricePerUnit": {
            "type": "number",
            "format": "double"
          },
          "availableQuantity": {
            "type": "integer",
            "format": "int32"
          },
          "estimatedDeliveryDays": {
            "type": "integer",
            "format": "int32"
          }
        },
        "additionalProperties": false
      },
      "ProductRequestDto": {
        "type": "object",
        "properties": {
          "productId": {
            "type": "string",
            "nullable": true
          },
          "quantity": {
            "type": "integer",
            "format": "int32"
          }
        },
        "additionalProperties": false
      },
      "QuotationRequestDto": {
        "type": "object",
        "properties": {
          "requestId": {
            "type": "string",
            "nullable": true
          },
          "requestDate": {
            "type": "string",
            "format": "date-time",
            "nullable": true
          },
          "productRequests": {
            "type": "array",
            "items": {
              "$ref": "#/components/schemas/ProductRequestDto"
            },
            "nullable": true
          }
        },
        "additionalProperties": false
      },
      "QuotationResponseDto": {
        "type": "object",
        "properties": {
          "requestId": {
            "type": "string",
            "nullable": true
          },
          "responseDate": {
            "type": "string",
            "format": "date-time",
            "nullable": true
          },
          "distributerId": {
            "type": "string",
            "nullable": true
          },
          "productQuotes": {
            "type": "array",
            "items": {
              "$ref": "#/components/schemas/ProductQuoteInfoReadDto"
            },
            "nullable": true
          }
        },
        "additionalProperties": false
      }
    }
  }
}